README.md
setup.py
smartninja_mongo/__init__.py
smartninja_mongo/bson.py
smartninja_mongo/connection.py
smartninja_mongo/environment.py
smartninja_mongo/odm.py
smartninja_mongo.egg-info/PKG-INFO
smartninja_mongo.egg-info/SOURCES.txt
smartninja_mongo.egg-info/dependency_links.txt
smartninja_mongo.egg-info/requires.txt
smartninja_mongo.egg-info/top_level.txt