Metadata-Version: 2.1
Name: smartninja-mongo
Version: 0.5
Summary: SmartNinja Mongo - a simple MongoDB & TinyDB wrapper.
Home-page: https://github.com/smartninja/smartninja-mongo
Author: Matej Ramuta
Author-email: matej.ramuta@gmail.com
License: MIT
Platform: UNKNOWN
Classifier: Programming Language :: Python :: 3
Classifier: License :: OSI Approved :: MIT License
Classifier: Operating System :: OS Independent
